borg_find/__init__.py
borg_find/borg.py
borg_find/cli.py
borg_find/filters.py
borg_find/model.py
borg_find/ui.py
borg_find/utils.py
borg_find-0.2.0.dist-info/entry_points.txt
borg_find-0.2.0.dist-info/LICENSE
borg_find-0.2.0.dist-info/WHEEL
borg_find-0.2.0.dist-info/METADATA
borg_find-0.2.0.dist-info/RECORD
