Metadata-Version: 2.1
Name: borg-find
Version: 0.2.0
Summary: Tool to search files in borg archives
License: Apache-2.0
Author: Sébastien MB
Author-email: seb@essembeh.org
Requires-Python: >=3.8,<4.0
Classifier: Development Status :: 4 - Beta
Classifier: License :: OSI Approved :: Apache Software License
Classifier: Programming Language :: Python :: 3
Classifier: Programming Language :: Python :: 3.10
Classifier: Programming Language :: Python :: 3.8
Classifier: Programming Language :: Python :: 3.9
Classifier: Topic :: Utilities
Requires-Dist: cached-property
Requires-Dist: colorama
